mysql_quote_identifiers/__init__.py
mysql_quote_identifiers/reserved_words.py
mysql_quote_identifiers-0.0.2.dist-info/METADATA
mysql_quote_identifiers-0.0.2.dist-info/WHEEL
mysql_quote_identifiers-0.0.2.dist-info/licenses/LICENSE
mysql_quote_identifiers-0.0.2.dist-info/RECORD
