Metadata-Version: 2.4
Name: mysql-quote-identifiers
Version: 0.0.2
Summary: The python mysql connector has no way to safely quote identifiers like table names or database names. This library implements basic functions to do that.
Project-URL: Homepage, https://github.com/hazel-noack/mysql-quote-identifiers
Project-URL: Issues, https://github.com/hazel-noack/mysql-quote-identifiers/issues
Author-email: Hazel Noack <hazel@webcontact.de>
License-File: LICENSE
Classifier: Operating System :: OS Independent
Classifier: Programming Language :: Python :: 3
Requires-Python: >=3.10
